winzy_calendar/__init__.py
winzy_calendar-0.1.dist-info/LICENSE
winzy_calendar-0.1.dist-info/METADATA
winzy_calendar-0.1.dist-info/WHEEL
winzy_calendar-0.1.dist-info/entry_points.txt
winzy_calendar-0.1.dist-info/top_level.txt
winzy_calendar-0.1.dist-info/RECORD
