Metadata-Version: 2.1
Name: winzy-calendar
Version: 0.1
Summary: Calendar in windows commandline
Author: Sukhbinder Singh
License: Apache-2.0
Project-URL: Homepage, https://github.com/sukhbinder/winzy-calendar
Project-URL: Changelog, https://github.com/sukhbinder/winzy-calendar/releases
Project-URL: Issues, https://github.com/sukhbinder/winzy-calendar/issues
Project-URL: CI, https://github.com/sukhbinder/winzy-calendar/actions
Classifier: License :: OSI Approved :: Apache Software License
License-File: LICENSE
Requires-Dist: winzy
Provides-Extra: test
Requires-Dist: pytest ; extra == 'test'
